LICENSE.txt
MANIFEST.in
README.md
requirements.txt
setup.cfg
setup.py
microservice_template_core/__init__.py
microservice_template_core/core.py
microservice_template_core.egg-info/PKG-INFO
microservice_template_core.egg-info/SOURCES.txt
microservice_template_core.egg-info/dependency_links.txt
microservice_template_core.egg-info/entry_points.txt
microservice_template_core.egg-info/not-zip-safe
microservice_template_core.egg-info/requires.txt
microservice_template_core.egg-info/top_level.txt
microservice_template_core/api/__init__.py
microservice_template_core/api/namespaces/__init__.py
microservice_template_core/api/namespaces/core_endpoints.py
microservice_template_core/decorators/__init__.py
microservice_template_core/decorators/auth_decorator.py
microservice_template_core/settings/__init__.py
microservice_template_core/settings/global_settings.py
microservice_template_core/tools/__init__.py
microservice_template_core/tools/aerospike_client.py
microservice_template_core/tools/db.py
microservice_template_core/tools/flask_restplus.py
microservice_template_core/tools/kafka_confluent_consumer.py
microservice_template_core/tools/kafka_confluent_producer.py
microservice_template_core/tools/logger.py
microservice_template_core/tools/prometheus_metrics.py
microservice_template_core/tools/tracer.py