Metadata-Version: 1.0
Name: microservice-template-core
Version: 2.4.0
Summary: Microservice template core
Home-page: UNKNOWN
Author: UNKNOWN
Author-email: UNKNOWN
License: UNKNOWN
Platform: UNKNOWN
